aeifdataset/__init__.py
aeifdataset/core.py
aeifdataset/data/__init__.py
aeifdataset/data/agent.py
aeifdataset/data/data.py
aeifdataset/data/frame.py
aeifdataset/data/metadata.py
aeifdataset/data/sensors.py
aeifdataset/develop/__init__.py
aeifdataset/develop/tests.py
aeifdataset/develop/visualisation.py
aeifdataset/miscellaneous/__init__.py
aeifdataset/miscellaneous/error_exceptions.py
aeifdataset/miscellaneous/helper.py
aeifdataset/miscellaneous/variables.py
aeifdataset/utils/__init__.py
aeifdataset/utils/fusion.py
aeifdataset/utils/image.py
aeifdataset/utils/managing.py
aeifdataset/utils/transformation.py
aeifdataset/utils/visualisation.py
aeif_dataset-1.2.1.dist-info/LICENSE
aeif_dataset-1.2.1.dist-info/METADATA
aeif_dataset-1.2.1.dist-info/WHEEL
aeif_dataset-1.2.1.dist-info/top_level.txt
aeif_dataset-1.2.1.dist-info/RECORD
